recaptcha_domain_replicator/__init__.py
recaptcha_domain_replicator/__main__.py
recaptcha_domain_replicator/browser_config.py
recaptcha_domain_replicator/captcha_replicator.py
recaptcha_domain_replicator/certificates.py
recaptcha_domain_replicator/constants.py
recaptcha_domain_replicator/demo.py
recaptcha_domain_replicator/hosts_manager.py
recaptcha_domain_replicator/html_builder.py
recaptcha_domain_replicator/logging_utils.py
recaptcha_domain_replicator/proxy_auth_extension.py
recaptcha_domain_replicator/proxy_utils.py
recaptcha_domain_replicator/py.typed
recaptcha_domain_replicator/server_manager.py
recaptcha_domain_replicator/token_monitor.py
recaptcha_domain_replicator-1.0.6.dist-info/licenses/LICENSE
recaptcha_domain_replicator-1.0.6.dist-info/METADATA
recaptcha_domain_replicator-1.0.6.dist-info/WHEEL
recaptcha_domain_replicator-1.0.6.dist-info/entry_points.txt
recaptcha_domain_replicator-1.0.6.dist-info/top_level.txt
recaptcha_domain_replicator-1.0.6.dist-info/RECORD
