Metadata-Version: 2.4
Name: recaptcha-domain-replicator
Version: 1.0.6
Summary: Serve a local replica of a reCAPTCHA widget and capture the token.
License-Expression: MIT
Project-URL: Homepage, https://github.com/DannyLuna17/RecaptchaDomainReplicator
Project-URL: Repository, https://github.com/DannyLuna17/RecaptchaDomainReplicator
Project-URL: Issues, https://github.com/DannyLuna17/RecaptchaDomainReplicator/issues
Keywords: recaptcha,captcha,automation,flask,drissionpage
Classifier: Programming Language :: Python :: 3
Classifier: Programming Language :: Python :: 3 :: Only
Requires-Python: >=3.9
License-File: LICENSE
Requires-Dist: DrissionPage>=4.1.1.2
Requires-Dist: Flask>=2.0
Requires-Dist: pyOpenSSL>=19.0
Provides-Extra: dev
Requires-Dist: pytest>=7.0; extra == "dev"
Requires-Dist: ruff>=0.5; extra == "dev"
Requires-Dist: mypy>=1.0; extra == "dev"
Dynamic: license-file
